invarpy/__init__.py
invarpy/common.py
invarpy/invarpy.py
invarpy/nopbc_estimators.py
invarpy/pbc_estimators.py
invarpy-1.3.0.dist-info/LICENSE.txt
invarpy-1.3.0.dist-info/METADATA
invarpy-1.3.0.dist-info/WHEEL
invarpy-1.3.0.dist-info/top_level.txt
invarpy-1.3.0.dist-info/RECORD
