Metadata-Version: 2.1
Name: invarpy
Version: 1.3.0
Summary: Invariance estiators for Python
Home-page: https://github.com/buschinelli-joao/invarpy
Author: Joao Buschinelli
Author-email: joao.correabuschinelli@mail.mcgill.ca
Project-URL: Bug Tracker, https://github.com/pypa/sampleproject/issues
Classifier: Programming Language :: Python :: 3
Classifier: License :: OSI Approved :: MIT License
Classifier: Operating System :: OS Independent
Requires-Python: >=3.6
License-File: LICENSE.txt
